object_diff/__init__.py
object_diff-0.0.1.dist-info/COPYING
object_diff-0.0.1.dist-info/COPYING.LESSER
object_diff-0.0.1.dist-info/WHEEL
object_diff-0.0.1.dist-info/METADATA
object_diff-0.0.1.dist-info/RECORD
